groq_gradio/__init__.py
groq_gradio-0.0.1.dist-info/METADATA
groq_gradio-0.0.1.dist-info/WHEEL
groq_gradio-0.0.1.dist-info/RECORD
