Metadata-Version: 2.3
Name: groq-gradio
Version: 0.0.1
Summary: A Python package for creating Gradio applications with Groq models
Project-URL: homepage, https://github.com/AK391/groq-gradio
Project-URL: repository, https://github.com/AK391/groq-gradio
Author-email: AK <ahsen.khaliq@gmail.com>
Classifier: License :: OSI Approved :: MIT License
Classifier: Operating System :: OS Independent
Classifier: Programming Language :: Python :: 3
Requires-Python: >=3.10
Requires-Dist: gradio>=5.0.0b5
Requires-Dist: groq
Provides-Extra: dev
Requires-Dist: pytest; extra == 'dev'
